{
  "name": "Harold Mayot",
  "age": "24",
  "country": "France",
  "height": "5'11\" (180cm)",
  "weight": "176 lbs (80kg)",
  "plays": "Right-Handed, Two-Handed Backhand",
  "coach": "Ruben Ramirez Hidalgo",
  "turned_pro": "2020",
  "birthplace": "Metz, France",
  "rank": 156,
  "points": "380",
  "career_high_rank": "103",
  "ytd_rank": "168",
  "image_url": "http://www.atptour.com/-/media/alias/player-gladiator-headshot/m0g4",
  "url": "https://www.atptour.com/en/players/harold-mayot/m0g4/overview",
  "player_id": "M0G4",
  "updated_at": "2026-02-13T18:43:55.571274+00:00",
  "ytd_won_lost": "0 - 0",
  "ytd_titles": "0",
  "ytd_prize_money": "$38,771",
  "career_prize_money": "$1,191,485"
}