{
  "name": "Daniel Altmaier",
  "age": "27",
  "country": "Germany",
  "height": "6'2\" (188cm)",
  "weight": "176 lbs (80kg)",
  "plays": "Right-Handed, One-Handed Backhand",
  "coach": "Martin Cuevas",
  "turned_pro": "2014",
  "birthplace": "Kempen, Germany",
  "rank": 44,
  "points": "1083",
  "career_high_rank": "44",
  "ytd_rank": "44",
  "image_url": "http://www.atptour.com/-/media/alias/player-gladiator-headshot/ae14",
  "url": "https://www.atptour.com/en/players/daniel-altmaier/ae14/overview",
  "player_id": "AE14",
  "updated_at": "2026-02-08T14:41:44.736436+00:00",
  "ytd_won_lost": "0 - 3",
  "ytd_titles": "0",
  "ytd_prize_money": "$115,435",
  "career_prize_money": "$4,921,798"
}